chunkformer/__init__.py
chunkformer/chunkformer_model.py
chunkformer/bin/__init__.py
chunkformer/bin/alignment.py
chunkformer/bin/average_model.py
chunkformer/bin/classify.py
chunkformer/bin/recognize.py
chunkformer/bin/train.py
chunkformer/dataset/__init__.py
chunkformer/dataset/datapipes.py
chunkformer/dataset/dataset.py
chunkformer/dataset/kaldi_io.py
chunkformer/dataset/processor.py
chunkformer/dataset/wav_distortion.py
chunkformer/modules/__init__.py
chunkformer/modules/asr_model.py
chunkformer/modules/attention.py
chunkformer/modules/classification_model.py
chunkformer/modules/cmvn.py
chunkformer/modules/convolution.py
chunkformer/modules/ctc.py
chunkformer/modules/decoder.py
chunkformer/modules/decoder_layer.py
chunkformer/modules/embedding.py
chunkformer/modules/encoder.py
chunkformer/modules/encoder_layer.py
chunkformer/modules/label_smoothing_loss.py
chunkformer/modules/norm.py
chunkformer/modules/positionwise_feed_forward.py
chunkformer/modules/search.py
chunkformer/modules/subsampling.py
chunkformer/modules/swish.py
chunkformer/text/__init__.py
chunkformer/text/base_tokenizer.py
chunkformer/text/bpe_tokenizer.py
chunkformer/text/char_tokenizer.py
chunkformer/text/tokenize_utils.py
chunkformer/transducer/__init__.py
chunkformer/transducer/joint.py
chunkformer/transducer/predictor.py
chunkformer/transducer/transducer.py
chunkformer/transducer/search/__init__.py
chunkformer/transducer/search/greedy_search.py
chunkformer/transducer/search/prefix_beam_search.py
chunkformer/utils/__init__.py
chunkformer/utils/checkpoint.py
chunkformer/utils/class_utils.py
chunkformer/utils/cmvn.py
chunkformer/utils/common.py
chunkformer/utils/config.py
chunkformer/utils/context_graph.py
chunkformer/utils/executor.py
chunkformer/utils/file_utils.py
chunkformer/utils/fsdp_utils.py
chunkformer/utils/init_dataset.py
chunkformer/utils/init_model.py
chunkformer/utils/init_tokenizer.py
chunkformer/utils/mask.py
chunkformer/utils/model_utils.py
chunkformer/utils/scheduler.py
chunkformer-1.2.2.dist-info/licenses/LICENSE
chunkformer-1.2.2.dist-info/METADATA
chunkformer-1.2.2.dist-info/WHEEL
chunkformer-1.2.2.dist-info/entry_points.txt
chunkformer-1.2.2.dist-info/top_level.txt
chunkformer-1.2.2.dist-info/RECORD
