Metadata-Version: 2.4
Name: chunkformer
Version: 1.2.2
Summary: ChunkFormer: Masked Chunking Conformer For Long-Form Speech Transcription
Author-email: khanld <khanhld218@gmail.com>
License: CC-BY-4.0
Project-URL: Homepage, https://github.com/khanld/chunkformer
Project-URL: Documentation, https://github.com/khanld/chunkformer/blob/main/README.md
Project-URL: Repository, https://github.com/khanld/chunkformer
Project-URL: Bug Reports, https://github.com/khanld/chunkformer/issues
Project-URL: Paper, https://github.com/khanld/chunkformer/blob/main/docs/paper.pdf
Keywords: speech-recognition,asr,chunkformer,transformer,conformer,pytorch,long-form-audio,machine-learning,deep-learning
Classifier: Development Status :: 5 - Production/Stable
Classifier: Intended Audience :: Science/Research
Classifier: Intended Audience :: Developers
Classifier: License :: Other/Proprietary License
Classifier: Operating System :: OS Independent
Classifier: Programming Language :: Python :: 3
Classifier: Programming Language :: Python :: 3.11
Classifier: Topic :: Scientific/Engineering :: Artificial Intelligence
Classifier: Topic :: Multimedia :: Sound/Audio :: Speech
Requires-Python: >=3.11
License-File: LICENSE
Requires-Dist: torch>=2.5.1
Requires-Dist: torchaudio>=2.5.1
Requires-Dist: transformers>=4.20.0
Requires-Dist: PyYAML>=5.4.0
Requires-Dist: pandas>=1.3.0
Requires-Dist: tqdm>=4.62.0
Requires-Dist: jiwer>=2.3.0
Requires-Dist: colorama>=0.4.4
Requires-Dist: pydub>=0.25.0
Requires-Dist: huggingface_hub>=0.10.0
Requires-Dist: Pillow
Requires-Dist: sentencepiece
Requires-Dist: tensorboard
Requires-Dist: tensorboardX
Requires-Dist: textgrid
Requires-Dist: deepspeed>=0.14.0
Requires-Dist: librosa
Requires-Dist: langid
Provides-Extra: dev
Requires-Dist: pytest>=6.0.0; extra == "dev"
Requires-Dist: black==25.9.0; extra == "dev"
Requires-Dist: flake8==6.0.0; extra == "dev"
Requires-Dist: flake8-pyproject>=1.2.0; extra == "dev"
Requires-Dist: isort==5.12.0; extra == "dev"
Requires-Dist: mypy==1.5.1; extra == "dev"
Requires-Dist: pre-commit>=3.0.0; extra == "dev"
Requires-Dist: types-PyYAML>=6.0.0; extra == "dev"
Requires-Dist: autopep8>=2.0.0; extra == "dev"
Requires-Dist: autoflake>=2.0.0; extra == "dev"
Dynamic: license-file
